{"doc_id": "0dd21ec6cc744888b347a6398482c163", "doc_name": "JAP Loab", "doc_version": "b28970da6639491d4015dfd78ad84914", "format": "onnx", "version": 11, "inputs": {"Image": {"dtype": "float32", "shape": [null, 224, 224, 3], "name": "Image:0"}}, "outputs": {"Confidences": {"dtype": "float32", "shape": [null, 7], "name": "Confidences"}}, "tags": [], "classes": {"Label": ["Black1Pc", "Chrome1Pc", "ChromeBlack2Pc", "ChromeBlue2Pc", "GlossBlackBlue2Pc", "GlossBlackGray2Pc", "GrayBlack2Pc", "GrayBlue2Pc", "GrayGold2Pc", "GrayRed2Pc"]}, "filename": "model.onnx", "export_model_version": 1}